{"Code" : "OK","ErrorMessage" : "","FullError" : "","ChargedAnalysisResUnits" : 1000,"ChargedRetrievalResUnits" : 100,"Cmd" : "GetTopics","IndexBuildDate" : "2015-10-14 02:12:47","IndexType" : 0,"RemainingAnalysisResUnits" : 99737000,"RemainingRetrievalResUnits" : 19981847,"ServerBuild" : "2015-10-23 14:17:16","ServerName" : "HUMMERR","ServerVersion" : "1.0.5774.23918","UniqueIndexID" : "20151014021247-HISTORICAL","DataTables" : {"Topics" : {"Headers" : {"Count" : 100,"From" : 0,"SortBy" : "topicaltrustflow&links","SortOrder" : "desc","TotalResults" : 593},"Data" : [{ "Topic" : "Computers/Internet", "Links" : 73927, "TopicalTrustFlow" : 91, "LinksFromRefDomains" : 1246881, "RefDomains" : 4151, "Pages" : 9036 },{ "Topic" : "Arts/Television", "Links" : 489591, "TopicalTrustFlow" : 53, "LinksFromRefDomains" : 18991770, "RefDomains" : 9021, "Pages" : 26468 },{ "Topic" : "Computers/Internet/On the Web", "Links" : 522679, "TopicalTrustFlow" : 52, "LinksFromRefDomains" : 8581931, "RefDomains" : 23725, "Pages" : 25507 },{ "Topic" : "News/Newspapers", "Links" : 180823, "TopicalTrustFlow" : 52, "LinksFromRefDomains" : 12366100, "RefDomains" : 18642, "Pages" : 49689 },{ "Topic" : "News/Media Industry", "Links" : 528196, "TopicalTrustFlow" : 50, "LinksFromRefDomains" : 6261580, "RefDomains" : 16883, "Pages" : 50189 },{ "Topic" : "Society/Issues", "Links" : 946810, "TopicalTrustFlow" : 49, "LinksFromRefDomains" : 11014592, "RefDomains" : 23029, "Pages" : 100480 },{ "Topic" : "Society/Politics", "Links" : 814066, "TopicalTrustFlow" : 49, "LinksFromRefDomains" : 17867848, "RefDomains" : 18324, "Pages" : 62240 },{ "Topic" : "Science/Environment", "Links" : 47851, "TopicalTrustFlow" : 49, "LinksFromRefDomains" : 952491, "RefDomains" : 3583, "Pages" : 5223 },{ "Topic" : "Health/Specific Substances", "Links" : 2270, "TopicalTrustFlow" : 47, "LinksFromRefDomains" : 7381, "RefDomains" : 11, "Pages" : 3188 },{ "Topic" : "Sports/Basketball", "Links" : 15552, "TopicalTrustFlow" : 44, "LinksFromRefDomains" : 559479, "RefDomains" : 426, "Pages" : 471 },{ "Topic" : "Business/Transportation and Logistics", "Links" : 39077, "TopicalTrustFlow" : 43, "LinksFromRefDomains" : 1862483, "RefDomains" : 4038, "Pages" : 16898 },{ "Topic" : "Computers/Data Communications", "Links" : 2005, "TopicalTrustFlow" : 43, "LinksFromRefDomains" : 57980, "RefDomains" : 378, "Pages" : 24965 },{ "Topic" : "Recreation/Travel", "Links" : 920690, "TopicalTrustFlow" : 42, "LinksFromRefDomains" : 7858432, "RefDomains" : 23067, "Pages" : 21842 },{ "Topic" : "Society/People", "Links" : 341757, "TopicalTrustFlow" : 42, "LinksFromRefDomains" : 7072928, "RefDomains" : 16847, "Pages" : 54904 },{ "Topic" : "News/Headline Links", "Links" : 215518, "TopicalTrustFlow" : 42, "LinksFromRefDomains" : 2188110, "RefDomains" : 1282, "Pages" : 32084 },{ "Topic" : "Arts/Literature", "Links" : 192729, "TopicalTrustFlow" : 42, "LinksFromRefDomains" : 2609696, "RefDomains" : 8100, "Pages" : 38490 },{ "Topic" : "Society/Religion and Spirituality", "Links" : 372867, "TopicalTrustFlow" : 41, "LinksFromRefDomains" : 7258660, "RefDomains" : 16012, "Pages" : 44473 },{ "Topic" : "Reference/Education", "Links" : 328098, "TopicalTrustFlow" : 41, "LinksFromRefDomains" : 13554698, "RefDomains" : 30989, "Pages" : 27572 },{ "Topic" : "Recreation/Humor", "Links" : 93969, "TopicalTrustFlow" : 41, "LinksFromRefDomains" : 3493132, "RefDomains" : 4749, "Pages" : 17343 },{ "Topic" : "Sports/Soccer", "Links" : 386366, "TopicalTrustFlow" : 40, "LinksFromRefDomains" : 4718044, "RefDomains" : 7441, "Pages" : 10193 },{ "Topic" : "Recreation/Food", "Links" : 71798, "TopicalTrustFlow" : 40, "LinksFromRefDomains" : 2507182, "RefDomains" : 5184, "Pages" : 8924 },{ "Topic" : "Health/Conditions and Diseases", "Links" : 65607, "TopicalTrustFlow" : 40, "LinksFromRefDomains" : 1616477, "RefDomains" : 4639, "Pages" : 12891 },{ "Topic" : "Recreation/Tobacco", "Links" : 16029, "TopicalTrustFlow" : 40, "LinksFromRefDomains" : 127194, "RefDomains" : 149, "Pages" : 14092 },{ "Topic" : "Science/Agriculture", "Links" : 8925, "TopicalTrustFlow" : 40, "LinksFromRefDomains" : 79236, "RefDomains" : 676, "Pages" : 1768 },{ "Topic" : "Science/Social Sciences", "Links" : 209105, "TopicalTrustFlow" : 39, "LinksFromRefDomains" : 2957795, "RefDomains" : 9240, "Pages" : 17890 },{ "Topic" : "Society", "Links" : 198859, "TopicalTrustFlow" : 39, "LinksFromRefDomains" : 1949717, "RefDomains" : 4114, "Pages" : 16228 },{ "Topic" : "Sports/Running", "Links" : 12187, "TopicalTrustFlow" : 39, "LinksFromRefDomains" : 93463, "RefDomains" : 531, "Pages" : 840 },{ "Topic" : "Computers/Data Formats", "Links" : 8155, "TopicalTrustFlow" : 39, "LinksFromRefDomains" : 338555, "RefDomains" : 1998, "Pages" : 1779 },{ "Topic" : "Arts/Music", "Links" : 218995, "TopicalTrustFlow" : 38, "LinksFromRefDomains" : 3484400, "RefDomains" : 17540, "Pages" : 14127 },{ "Topic" : "Science/Science in Society", "Links" : 100755, "TopicalTrustFlow" : 38, "LinksFromRefDomains" : 400207, "RefDomains" : 951, "Pages" : 6372 },{ "Topic" : "News/Magazines and E-zines", "Links" : 84008, "TopicalTrustFlow" : 38, "LinksFromRefDomains" : 2102772, "RefDomains" : 6221, "Pages" : 16673 },{ "Topic" : "Arts/Design", "Links" : 70760, "TopicalTrustFlow" : 38, "LinksFromRefDomains" : 939693, "RefDomains" : 4110, "Pages" : 9304 },{ "Topic" : "Society/Paranormal", "Links" : 43337, "TopicalTrustFlow" : 38, "LinksFromRefDomains" : 692855, "RefDomains" : 2197, "Pages" : 5215 },{ "Topic" : "Home/Consumer Information", "Links" : 23099, "TopicalTrustFlow" : 38, "LinksFromRefDomains" : 7961400, "RefDomains" : 2796, "Pages" : 4273 },{ "Topic" : "Business/Marketing and Advertising", "Links" : 148937, "TopicalTrustFlow" : 37, "LinksFromRefDomains" : 1846374, "RefDomains" : 4867, "Pages" : 6920 },{ "Topic" : "News/Journalism", "Links" : 108546, "TopicalTrustFlow" : 37, "LinksFromRefDomains" : 732625, "RefDomains" : 2634, "Pages" : 8201 },{ "Topic" : "Science/Technology", "Links" : 41623, "TopicalTrustFlow" : 37, "LinksFromRefDomains" : 912009, "RefDomains" : 6219, "Pages" : 8755 },{ "Topic" : "Health/Mental Health", "Links" : 30490, "TopicalTrustFlow" : 37, "LinksFromRefDomains" : 653357, "RefDomains" : 2297, "Pages" : 4410 },{ "Topic" : "Society/Activism", "Links" : 28983, "TopicalTrustFlow" : 37, "LinksFromRefDomains" : 492655, "RefDomains" : 1323, "Pages" : 4684 },{ "Topic" : "Arts/Entertainment", "Links" : 24012, "TopicalTrustFlow" : 37, "LinksFromRefDomains" : 541231, "RefDomains" : 2033, "Pages" : 11604 },{ "Topic" : "Arts/People", "Links" : 8839, "TopicalTrustFlow" : 37, "LinksFromRefDomains" : 288613, "RefDomains" : 774, "Pages" : 4112 },{ "Topic" : "Society/Military", "Links" : 7709, "TopicalTrustFlow" : 37, "LinksFromRefDomains" : 324187, "RefDomains" : 1063, "Pages" : 1018 },{ "Topic" : "Arts/Movies", "Links" : 103448, "TopicalTrustFlow" : 36, "LinksFromRefDomains" : 948974, "RefDomains" : 5420, "Pages" : 14190 },{ "Topic" : "Society/History", "Links" : 79563, "TopicalTrustFlow" : 36, "LinksFromRefDomains" : 606877, "RefDomains" : 2850, "Pages" : 6430 },{ "Topic" : "Business/Financial Services", "Links" : 57836, "TopicalTrustFlow" : 36, "LinksFromRefDomains" : 1077923, "RefDomains" : 4741, "Pages" : 10931 },{ "Topic" : "Computers/Programming/Languages", "Links" : 39195, "TopicalTrustFlow" : 36, "LinksFromRefDomains" : 1171616, "RefDomains" : 9016, "Pages" : 3466 },{ "Topic" : "Science/Biology", "Links" : 28104, "TopicalTrustFlow" : 36, "LinksFromRefDomains" : 483607, "RefDomains" : 2247, "Pages" : 4268 },{ "Topic" : "Computers/Software/Internet", "Links" : 25931, "TopicalTrustFlow" : 36, "LinksFromRefDomains" : 1028085, "RefDomains" : 4824, "Pages" : 3687 },{ "Topic" : "Health/Alternative", "Links" : 16645, "TopicalTrustFlow" : 36, "LinksFromRefDomains" : 228684, "RefDomains" : 1298, "Pages" : 4658 },{ "Topic" : "Home/Gardening", "Links" : 15444, "TopicalTrustFlow" : 36, "LinksFromRefDomains" : 159376, "RefDomains" : 1306, "Pages" : 6554 },{ "Topic" : "Business/News and Media", "Links" : 12489, "TopicalTrustFlow" : 36, "LinksFromRefDomains" : 146607, "RefDomains" : 841, "Pages" : 2058 },{ "Topic" : "Arts/Art History", "Links" : 4575, "TopicalTrustFlow" : 36, "LinksFromRefDomains" : 107250, "RefDomains" : 557, "Pages" : 794 },{ "Topic" : "Science/Publications", "Links" : 1910, "TopicalTrustFlow" : 36, "LinksFromRefDomains" : 61203, "RefDomains" : 283, "Pages" : 1865 },{ "Topic" : "Arts/Radio", "Links" : 402298, "TopicalTrustFlow" : 35, "LinksFromRefDomains" : 1554307, "RefDomains" : 6841, "Pages" : 14254 },{ "Topic" : "Society/Government", "Links" : 153544, "TopicalTrustFlow" : 35, "LinksFromRefDomains" : 7629049, "RefDomains" : 11430, "Pages" : 10535 },{ "Topic" : "Health", "Links" : 61138, "TopicalTrustFlow" : 35, "LinksFromRefDomains" : 337589, "RefDomains" : 1930, "Pages" : 4736 },{ "Topic" : "Reference/Museums", "Links" : 55638, "TopicalTrustFlow" : 35, "LinksFromRefDomains" : 2630794, "RefDomains" : 3696, "Pages" : 6658 },{ "Topic" : "Health/Medicine", "Links" : 44749, "TopicalTrustFlow" : 35, "LinksFromRefDomains" : 923178, "RefDomains" : 2217, "Pages" : 4343 },{ "Topic" : "Business/Arts and Entertainment", "Links" : 43166, "TopicalTrustFlow" : 35, "LinksFromRefDomains" : 1377131, "RefDomains" : 3062, "Pages" : 3520 },{ "Topic" : "Computers/Software/Operating Systems", "Links" : 36004, "TopicalTrustFlow" : 35, "LinksFromRefDomains" : 2332454, "RefDomains" : 8188, "Pages" : 3600 },{ "Topic" : "Science/Earth Sciences", "Links" : 35107, "TopicalTrustFlow" : 35, "LinksFromRefDomains" : 389572, "RefDomains" : 1134, "Pages" : 5602 },{ "Topic" : "Business/Business Services", "Links" : 14850, "TopicalTrustFlow" : 35, "LinksFromRefDomains" : 434389, "RefDomains" : 2543, "Pages" : 2099 },{ "Topic" : "Computers/History", "Links" : 10202, "TopicalTrustFlow" : 35, "LinksFromRefDomains" : 292712, "RefDomains" : 456, "Pages" : 2441 },{ "Topic" : "Society/Crime", "Links" : 6918, "TopicalTrustFlow" : 35, "LinksFromRefDomains" : 72525, "RefDomains" : 461, "Pages" : 797 },{ "Topic" : "Science/Organizations", "Links" : 3276, "TopicalTrustFlow" : 35, "LinksFromRefDomains" : 56970, "RefDomains" : 654, "Pages" : 801 },{ "Topic" : "Society/Holidays", "Links" : 3144, "TopicalTrustFlow" : 35, "LinksFromRefDomains" : 99091, "RefDomains" : 636, "Pages" : 924 },{ "Topic" : "Society/Support Groups", "Links" : 985, "TopicalTrustFlow" : 35, "LinksFromRefDomains" : 8742, "RefDomains" : 61, "Pages" : 253 },{ "Topic" : "Computers/Internet/Searching", "Links" : 738775, "TopicalTrustFlow" : 34, "LinksFromRefDomains" : 11018091, "RefDomains" : 35817, "Pages" : 29615 },{ "Topic" : "Computers/News and Media", "Links" : 96885, "TopicalTrustFlow" : 34, "LinksFromRefDomains" : 1773672, "RefDomains" : 3979, "Pages" : 9048 },{ "Topic" : "Computers/Internet/Web Design and Development", "Links" : 84443, "TopicalTrustFlow" : 34, "LinksFromRefDomains" : 2888927, "RefDomains" : 15370, "Pages" : 7940 },{ "Topic" : "News/Alternative", "Links" : 43421, "TopicalTrustFlow" : 34, "LinksFromRefDomains" : 327844, "RefDomains" : 1297, "Pages" : 16546 },{ "Topic" : "News/Analysis and Opinion", "Links" : 40600, "TopicalTrustFlow" : 34, "LinksFromRefDomains" : 339297, "RefDomains" : 748, "Pages" : 4619 },{ "Topic" : "Business", "Links" : 39317, "TopicalTrustFlow" : 34, "LinksFromRefDomains" : 1438972, "RefDomains" : 5796, "Pages" : 6504 },{ "Topic" : "Society/Philanthropy", "Links" : 31601, "TopicalTrustFlow" : 34, "LinksFromRefDomains" : 441104, "RefDomains" : 2155, "Pages" : 4078 },{ "Topic" : "Arts/Visual Arts", "Links" : 26417, "TopicalTrustFlow" : 34, "LinksFromRefDomains" : 508362, "RefDomains" : 2402, "Pages" : 5457 },{ "Topic" : "Arts", "Links" : 16290, "TopicalTrustFlow" : 34, "LinksFromRefDomains" : 356230, "RefDomains" : 2818, "Pages" : 19711 },{ "Topic" : "Arts/Architecture", "Links" : 15048, "TopicalTrustFlow" : 34, "LinksFromRefDomains" : 150276, "RefDomains" : 1553, "Pages" : 3669 },{ "Topic" : "Arts/Performing Arts", "Links" : 9795, "TopicalTrustFlow" : 34, "LinksFromRefDomains" : 402348, "RefDomains" : 1686, "Pages" : 2585 },{ "Topic" : "Shopping/Clothing", "Links" : 6556, "TopicalTrustFlow" : 34, "LinksFromRefDomains" : 187101, "RefDomains" : 1051, "Pages" : 771 },{ "Topic" : "Reference/Maps", "Links" : 4835, "TopicalTrustFlow" : 34, "LinksFromRefDomains" : 155148, "RefDomains" : 505, "Pages" : 822 },{ "Topic" : "Health/Nutrition", "Links" : 4145, "TopicalTrustFlow" : 34, "LinksFromRefDomains" : 390849, "RefDomains" : 386, "Pages" : 1682 },{ "Topic" : "Regional/Africa", "Links" : 106, "TopicalTrustFlow" : 34, "LinksFromRefDomains" : 13510, "RefDomains" : 62, "Pages" : 2524 },{ "Topic" : "Society/Law", "Links" : 150031, "TopicalTrustFlow" : 33, "LinksFromRefDomains" : 958385, "RefDomains" : 5582, "Pages" : 12859 },{ "Topic" : "Science/Anomalies and Alternative Science", "Links" : 48522, "TopicalTrustFlow" : 33, "LinksFromRefDomains" : 538127, "RefDomains" : 1136, "Pages" : 6372 },{ "Topic" : "News/Weblogs", "Links" : 46888, "TopicalTrustFlow" : 33, "LinksFromRefDomains" : 891293, "RefDomains" : 1794, "Pages" : 5653 },{ "Topic" : "Business/Real Estate", "Links" : 26307, "TopicalTrustFlow" : 33, "LinksFromRefDomains" : 437204, "RefDomains" : 2177, "Pages" : 2445 },{ "Topic" : "Society/Organizations", "Links" : 20115, "TopicalTrustFlow" : 33, "LinksFromRefDomains" : 467251, "RefDomains" : 2644, "Pages" : 4460 },{ "Topic" : "Regional/Asia", "Links" : 19139, "TopicalTrustFlow" : 33, "LinksFromRefDomains" : 2053568, "RefDomains" : 5878, "Pages" : 1235 },{ "Topic" : "Science/News and Media", "Links" : 13034, "TopicalTrustFlow" : 33, "LinksFromRefDomains" : 148430, "RefDomains" : 701, "Pages" : 8761 },{ "Topic" : "Science/Math", "Links" : 10302, "TopicalTrustFlow" : 33, "LinksFromRefDomains" : 113785, "RefDomains" : 1139, "Pages" : 2115 },{ "Topic" : "Computers/Hardware", "Links" : 9018, "TopicalTrustFlow" : 33, "LinksFromRefDomains" : 653856, "RefDomains" : 2150, "Pages" : 2746 },{ "Topic" : "Business/Electronics and Electrical", "Links" : 7121, "TopicalTrustFlow" : 33, "LinksFromRefDomains" : 151590, "RefDomains" : 809, "Pages" : 1239 },{ "Topic" : "Health/Reproductive Health", "Links" : 6453, "TopicalTrustFlow" : 33, "LinksFromRefDomains" : 784209, "RefDomains" : 439, "Pages" : 1577 },{ "Topic" : "Computers/Systems", "Links" : 6228, "TopicalTrustFlow" : 33, "LinksFromRefDomains" : 210701, "RefDomains" : 1446, "Pages" : 3147 },{ "Topic" : "Health/Beauty", "Links" : 3220, "TopicalTrustFlow" : 33, "LinksFromRefDomains" : 151970, "RefDomains" : 330, "Pages" : 1032 },{ "Topic" : "Health/Education", "Links" : 2778, "TopicalTrustFlow" : 33, "LinksFromRefDomains" : 23879, "RefDomains" : 102, "Pages" : 468 },{ "Topic" : "News/Weather", "Links" : 1884, "TopicalTrustFlow" : 33, "LinksFromRefDomains" : 58434, "RefDomains" : 510, "Pages" : 2289 },{ "Topic" : "Health/Women's Health", "Links" : 1446, "TopicalTrustFlow" : 33, "LinksFromRefDomains" : 15208, "RefDomains" : 190, "Pages" : 599 },{ "Topic" : "Shopping/Antiques and Collectibles", "Links" : 648, "TopicalTrustFlow" : 33, "LinksFromRefDomains" : 5457, "RefDomains" : 114, "Pages" : 297 },{ "Topic" : "News", "Links" : 148623, "TopicalTrustFlow" : 32, "LinksFromRefDomains" : 679942, "RefDomains" : 2661, "Pages" : 6136 }]}}}