{"Code" : "OK","ErrorMessage" : "","FullError" : "","ChargedAnalysisResUnits" : 1000,"ChargedRetrievalResUnits" : 100,"Cmd" : "GetTopics","IndexBuildDate" : "2015-10-14 02:12:47","IndexType" : 0,"RemainingAnalysisResUnits" : 99821000,"RemainingRetrievalResUnits" : 19990247,"ServerBuild" : "2015-10-23 14:17:16","ServerName" : "HUMMERR","ServerVersion" : "1.0.5774.23918","UniqueIndexID" : "20151014021247-HISTORICAL","DataTables" : {"Topics" : {"Headers" : {"Count" : 100,"From" : 0,"SortBy" : "topicaltrustflow&links","SortOrder" : "desc","TotalResults" : 597},"Data" : [{ "Topic" : "Reference/Education", "Links" : 12229548, "TopicalTrustFlow" : 81, "LinksFromRefDomains" : 458182342, "RefDomains" : 216997, "Pages" : 623606 },{ "Topic" : "Arts/Television", "Links" : 3354775, "TopicalTrustFlow" : 76, "LinksFromRefDomains" : 151546216, "RefDomains" : 27413, "Pages" : 304139 },{ "Topic" : "Computers/Internet/Searching", "Links" : 34578442, "TopicalTrustFlow" : 75, "LinksFromRefDomains" : 841865735, "RefDomains" : 240632, "Pages" : 919536 },{ "Topic" : "Computers/Software/Operating Systems", "Links" : 3341682, "TopicalTrustFlow" : 75, "LinksFromRefDomains" : 168992881, "RefDomains" : 54266, "Pages" : 183751 },{ "Topic" : "Computers/Software/Internet", "Links" : 8865374, "TopicalTrustFlow" : 72, "LinksFromRefDomains" : 88017934, "RefDomains" : 35180, "Pages" : 145412 },{ "Topic" : "Recreation/Travel", "Links" : 9477656, "TopicalTrustFlow" : 70, "LinksFromRefDomains" : 275406798, "RefDomains" : 140911, "Pages" : 497558 },{ "Topic" : "Society/Government", "Links" : 3755525, "TopicalTrustFlow" : 70, "LinksFromRefDomains" : 164406893, "RefDomains" : 71942, "Pages" : 240875 },{ "Topic" : "Computers/Internet/On the Web", "Links" : 9658744, "TopicalTrustFlow" : 69, "LinksFromRefDomains" : 809702067, "RefDomains" : 148787, "Pages" : 395681 },{ "Topic" : "Reference/Museums", "Links" : 1387200, "TopicalTrustFlow" : 69, "LinksFromRefDomains" : 38536695, "RefDomains" : 19023, "Pages" : 95120 },{ "Topic" : "Computers/Internet/History", "Links" : 22763, "TopicalTrustFlow" : 68, "LinksFromRefDomains" : 1201176, "RefDomains" : 762, "Pages" : 2536 },{ "Topic" : "Arts/Music", "Links" : 8937416, "TopicalTrustFlow" : 67, "LinksFromRefDomains" : 370402456, "RefDomains" : 78431, "Pages" : 442755 },{ "Topic" : "Society/Issues", "Links" : 8615124, "TopicalTrustFlow" : 67, "LinksFromRefDomains" : 203014326, "RefDomains" : 70468, "Pages" : 409240 },{ "Topic" : "Regional/Europe", "Links" : 3689387, "TopicalTrustFlow" : 67, "LinksFromRefDomains" : 164911310, "RefDomains" : 66035, "Pages" : 248122 },{ "Topic" : "News/Media Industry", "Links" : 12676805, "TopicalTrustFlow" : 66, "LinksFromRefDomains" : 177135584, "RefDomains" : 50776, "Pages" : 410909 },{ "Topic" : "Business/Investing", "Links" : 8969439, "TopicalTrustFlow" : 65, "LinksFromRefDomains" : 90808261, "RefDomains" : 18404, "Pages" : 349257 },{ "Topic" : "Society/Religion and Spirituality", "Links" : 6536231, "TopicalTrustFlow" : 64, "LinksFromRefDomains" : 157864091, "RefDomains" : 73599, "Pages" : 438234 },{ "Topic" : "Computers/Programming/Languages", "Links" : 2200048, "TopicalTrustFlow" : 64, "LinksFromRefDomains" : 155730203, "RefDomains" : 66321, "Pages" : 93683 },{ "Topic" : "Society/Philanthropy", "Links" : 748836, "TopicalTrustFlow" : 64, "LinksFromRefDomains" : 21750339, "RefDomains" : 10163, "Pages" : 59471 },{ "Topic" : "Arts/Movies", "Links" : 1845759, "TopicalTrustFlow" : 63, "LinksFromRefDomains" : 57537239, "RefDomains" : 18807, "Pages" : 105217 },{ "Topic" : "Society/Politics", "Links" : 7287190, "TopicalTrustFlow" : 62, "LinksFromRefDomains" : 147081270, "RefDomains" : 47362, "Pages" : 448173 },{ "Topic" : "News/Newspapers", "Links" : 6911296, "TopicalTrustFlow" : 62, "LinksFromRefDomains" : 215701743, "RefDomains" : 55620, "Pages" : 330661 },{ "Topic" : "Business/Transportation and Logistics", "Links" : 1456341, "TopicalTrustFlow" : 62, "LinksFromRefDomains" : 57655959, "RefDomains" : 25655, "Pages" : 82422 },{ "Topic" : "Science/Environment", "Links" : 1176530, "TopicalTrustFlow" : 62, "LinksFromRefDomains" : 38615690, "RefDomains" : 15672, "Pages" : 67796 },{ "Topic" : "Society/People", "Links" : 6169019, "TopicalTrustFlow" : 61, "LinksFromRefDomains" : 159625591, "RefDomains" : 67959, "Pages" : 515839 },{ "Topic" : "Science/Technology", "Links" : 4005773, "TopicalTrustFlow" : 61, "LinksFromRefDomains" : 98035008, "RefDomains" : 23550, "Pages" : 133673 },{ "Topic" : "Science/Social Sciences", "Links" : 3851463, "TopicalTrustFlow" : 61, "LinksFromRefDomains" : 118862845, "RefDomains" : 51092, "Pages" : 265651 },{ "Topic" : "Health/Conditions and Diseases", "Links" : 2024186, "TopicalTrustFlow" : 61, "LinksFromRefDomains" : 60751992, "RefDomains" : 19558, "Pages" : 95597 },{ "Topic" : "Computers/Internet/Web Design and Development", "Links" : 7999592, "TopicalTrustFlow" : 60, "LinksFromRefDomains" : 326202645, "RefDomains" : 120580, "Pages" : 315414 },{ "Topic" : "Science/Earth Sciences", "Links" : 2405072, "TopicalTrustFlow" : 60, "LinksFromRefDomains" : 17693855, "RefDomains" : 7347, "Pages" : 33336 },{ "Topic" : "Sports/Soccer", "Links" : 1077609, "TopicalTrustFlow" : 60, "LinksFromRefDomains" : 44440013, "RefDomains" : 16395, "Pages" : 56838 },{ "Topic" : "Business/Financial Services", "Links" : 1718327, "TopicalTrustFlow" : 59, "LinksFromRefDomains" : 70981550, "RefDomains" : 26553, "Pages" : 99340 },{ "Topic" : "Business/Consumer Goods and Services", "Links" : 918695, "TopicalTrustFlow" : 59, "LinksFromRefDomains" : 37720778, "RefDomains" : 20631, "Pages" : 45538 },{ "Topic" : "Business/Telecommunications", "Links" : 343033, "TopicalTrustFlow" : 59, "LinksFromRefDomains" : 10697857, "RefDomains" : 7361, "Pages" : 23253 },{ "Topic" : "Computers/Internet/Proxying and Filtering", "Links" : 225072, "TopicalTrustFlow" : 59, "LinksFromRefDomains" : 3182230, "RefDomains" : 1460, "Pages" : 2633 },{ "Topic" : "Regional/Asia", "Links" : 4609486, "TopicalTrustFlow" : 58, "LinksFromRefDomains" : 252774988, "RefDomains" : 113530, "Pages" : 282544 },{ "Topic" : "Society/Law", "Links" : 3212422, "TopicalTrustFlow" : 58, "LinksFromRefDomains" : 69335590, "RefDomains" : 34266, "Pages" : 221346 },{ "Topic" : "Arts/Comics", "Links" : 2110704, "TopicalTrustFlow" : 58, "LinksFromRefDomains" : 33103710, "RefDomains" : 12773, "Pages" : 69869 },{ "Topic" : "Society/Ethnicity", "Links" : 494535, "TopicalTrustFlow" : 58, "LinksFromRefDomains" : 9634476, "RefDomains" : 6735, "Pages" : 38915 },{ "Topic" : "Business/Arts and Entertainment", "Links" : 946551, "TopicalTrustFlow" : 57, "LinksFromRefDomains" : 44365835, "RefDomains" : 12837, "Pages" : 43497 },{ "Topic" : "News/Headline Links", "Links" : 805263, "TopicalTrustFlow" : 57, "LinksFromRefDomains" : 10250819, "RefDomains" : 2448, "Pages" : 77592 },{ "Topic" : "Computers/Multimedia", "Links" : 661809, "TopicalTrustFlow" : 57, "LinksFromRefDomains" : 27970218, "RefDomains" : 11177, "Pages" : 17244 },{ "Topic" : "Business/Agriculture and Forestry", "Links" : 578820, "TopicalTrustFlow" : 57, "LinksFromRefDomains" : 12617305, "RefDomains" : 8934, "Pages" : 35949 },{ "Topic" : "Computers/Software/Freeware", "Links" : 317205, "TopicalTrustFlow" : 57, "LinksFromRefDomains" : 12015474, "RefDomains" : 7126, "Pages" : 13493 },{ "Topic" : "Arts/Literature", "Links" : 2652111, "TopicalTrustFlow" : 56, "LinksFromRefDomains" : 77811992, "RefDomains" : 32630, "Pages" : 262880 },{ "Topic" : "Recreation/Outdoors", "Links" : 1710010, "TopicalTrustFlow" : 56, "LinksFromRefDomains" : 51929043, "RefDomains" : 22321, "Pages" : 59692 },{ "Topic" : "Business/Construction and Maintenance", "Links" : 974551, "TopicalTrustFlow" : 56, "LinksFromRefDomains" : 41075352, "RefDomains" : 19448, "Pages" : 69678 },{ "Topic" : "Science/Astronomy", "Links" : 342169, "TopicalTrustFlow" : 56, "LinksFromRefDomains" : 13544506, "RefDomains" : 6148, "Pages" : 21310 },{ "Topic" : "Regional/North America", "Links" : 7557575, "TopicalTrustFlow" : 55, "LinksFromRefDomains" : 128995954, "RefDomains" : 28239, "Pages" : 53213 },{ "Topic" : "Computers/Hardware", "Links" : 1664344, "TopicalTrustFlow" : 55, "LinksFromRefDomains" : 37560080, "RefDomains" : 14489, "Pages" : 43972 },{ "Topic" : "Society/Organizations", "Links" : 1346109, "TopicalTrustFlow" : 55, "LinksFromRefDomains" : 40453014, "RefDomains" : 17466, "Pages" : 90905 },{ "Topic" : "Recreation/Food", "Links" : 1249320, "TopicalTrustFlow" : 55, "LinksFromRefDomains" : 40629625, "RefDomains" : 17966, "Pages" : 63593 },{ "Topic" : "Recreation/Pets", "Links" : 987304, "TopicalTrustFlow" : 55, "LinksFromRefDomains" : 50855665, "RefDomains" : 23115, "Pages" : 45067 },{ "Topic" : "Computers/Data Formats", "Links" : 970690, "TopicalTrustFlow" : 55, "LinksFromRefDomains" : 32987981, "RefDomains" : 16388, "Pages" : 40150 },{ "Topic" : "Society", "Links" : 958803, "TopicalTrustFlow" : 55, "LinksFromRefDomains" : 45351896, "RefDomains" : 15272, "Pages" : 97298 },{ "Topic" : "Science/Biology", "Links" : 719834, "TopicalTrustFlow" : 55, "LinksFromRefDomains" : 33244216, "RefDomains" : 12058, "Pages" : 59259 },{ "Topic" : "Computers/Open Source", "Links" : 621159, "TopicalTrustFlow" : 55, "LinksFromRefDomains" : 19325090, "RefDomains" : 11914, "Pages" : 25669 },{ "Topic" : "Computers/Programming/Internet", "Links" : 505990, "TopicalTrustFlow" : 55, "LinksFromRefDomains" : 24071839, "RefDomains" : 7205, "Pages" : 16573 },{ "Topic" : "Business", "Links" : 2381817, "TopicalTrustFlow" : 54, "LinksFromRefDomains" : 112050506, "RefDomains" : 47372, "Pages" : 229234 },{ "Topic" : "Reference/Libraries", "Links" : 1728932, "TopicalTrustFlow" : 54, "LinksFromRefDomains" : 40978098, "RefDomains" : 26748, "Pages" : 94651 },{ "Topic" : "Recreation/Humor", "Links" : 1089982, "TopicalTrustFlow" : 54, "LinksFromRefDomains" : 43141676, "RefDomains" : 13391, "Pages" : 161334 },{ "Topic" : "Society/History", "Links" : 1035640, "TopicalTrustFlow" : 54, "LinksFromRefDomains" : 52751770, "RefDomains" : 12799, "Pages" : 65646 },{ "Topic" : "Arts/Photography", "Links" : 927858, "TopicalTrustFlow" : 54, "LinksFromRefDomains" : 37539702, "RefDomains" : 13746, "Pages" : 28253 },{ "Topic" : "Arts", "Links" : 874360, "TopicalTrustFlow" : 54, "LinksFromRefDomains" : 45667087, "RefDomains" : 15464, "Pages" : 39571 },{ "Topic" : "Health/Public Health and Safety", "Links" : 564694, "TopicalTrustFlow" : 54, "LinksFromRefDomains" : 12237240, "RefDomains" : 3380, "Pages" : 20797 },{ "Topic" : "Society/Activism", "Links" : 290643, "TopicalTrustFlow" : 54, "LinksFromRefDomains" : 7650701, "RefDomains" : 4347, "Pages" : 46297 },{ "Topic" : "Sports/Water Sports", "Links" : 193187, "TopicalTrustFlow" : 54, "LinksFromRefDomains" : 5529383, "RefDomains" : 2641, "Pages" : 7091 },{ "Topic" : "Arts/Radio", "Links" : 2463117, "TopicalTrustFlow" : 53, "LinksFromRefDomains" : 105400790, "RefDomains" : 20024, "Pages" : 144042 },{ "Topic" : "Home/Consumer Information", "Links" : 1932447, "TopicalTrustFlow" : 53, "LinksFromRefDomains" : 48122585, "RefDomains" : 15604, "Pages" : 92541 },{ "Topic" : "Recreation/Radio", "Links" : 786142, "TopicalTrustFlow" : 53, "LinksFromRefDomains" : 16547087, "RefDomains" : 8649, "Pages" : 18934 },{ "Topic" : "Recreation/Boating", "Links" : 295752, "TopicalTrustFlow" : 53, "LinksFromRefDomains" : 7646020, "RefDomains" : 5191, "Pages" : 12113 },{ "Topic" : "Society/Military", "Links" : 262236, "TopicalTrustFlow" : 53, "LinksFromRefDomains" : 14082439, "RefDomains" : 6180, "Pages" : 18404 },{ "Topic" : "Business/Biotechnology and Pharmaceuticals", "Links" : 141442, "TopicalTrustFlow" : 53, "LinksFromRefDomains" : 2482056, "RefDomains" : 1999, "Pages" : 6194 },{ "Topic" : "Computers/Software/ERP", "Links" : 4770, "TopicalTrustFlow" : 53, "LinksFromRefDomains" : 1165767, "RefDomains" : 221, "Pages" : 385 },{ "Topic" : "Computers/Internet", "Links" : 2699300, "TopicalTrustFlow" : 52, "LinksFromRefDomains" : 57118187, "RefDomains" : 23104, "Pages" : 86970 },{ "Topic" : "Business/Employment", "Links" : 1601195, "TopicalTrustFlow" : 52, "LinksFromRefDomains" : 121503771, "RefDomains" : 20747, "Pages" : 96630 },{ "Topic" : "Health/Mental Health", "Links" : 603708, "TopicalTrustFlow" : 52, "LinksFromRefDomains" : 36506270, "RefDomains" : 10083, "Pages" : 42065 },{ "Topic" : "Arts/Architecture", "Links" : 602385, "TopicalTrustFlow" : 52, "LinksFromRefDomains" : 14450480, "RefDomains" : 7023, "Pages" : 25019 },{ "Topic" : "Arts/Performing Arts", "Links" : 494135, "TopicalTrustFlow" : 52, "LinksFromRefDomains" : 15803516, "RefDomains" : 8519, "Pages" : 35220 },{ "Topic" : "Science/Math", "Links" : 491755, "TopicalTrustFlow" : 52, "LinksFromRefDomains" : 11658484, "RefDomains" : 6897, "Pages" : 21738 },{ "Topic" : "Business/Energy", "Links" : 430858, "TopicalTrustFlow" : 52, "LinksFromRefDomains" : 7998467, "RefDomains" : 6086, "Pages" : 34926 },{ "Topic" : "Home/Gardening", "Links" : 392563, "TopicalTrustFlow" : 52, "LinksFromRefDomains" : 15745653, "RefDomains" : 6442, "Pages" : 33306 },{ "Topic" : "Shopping/Health", "Links" : 228869, "TopicalTrustFlow" : 52, "LinksFromRefDomains" : 9023943, "RefDomains" : 3812, "Pages" : 10409 },{ "Topic" : "Computers/Companies", "Links" : 119987, "TopicalTrustFlow" : 52, "LinksFromRefDomains" : 15483832, "RefDomains" : 1964, "Pages" : 97947 },{ "Topic" : "Reference/Archives", "Links" : 32790, "TopicalTrustFlow" : 52, "LinksFromRefDomains" : 1484056, "RefDomains" : 532, "Pages" : 1680 },{ "Topic" : "Computers/Software/Editors", "Links" : 14192, "TopicalTrustFlow" : 52, "LinksFromRefDomains" : 6679998, "RefDomains" : 837, "Pages" : 591 },{ "Topic" : "Sports/Baseball", "Links" : 15508741, "TopicalTrustFlow" : 51, "LinksFromRefDomains" : 159279394, "RefDomains" : 6205, "Pages" : 116620 },{ "Topic" : "Business/Marketing and Advertising", "Links" : 2031409, "TopicalTrustFlow" : 51, "LinksFromRefDomains" : 64915965, "RefDomains" : 23414, "Pages" : 72706 },{ "Topic" : "Arts/Writers Resources", "Links" : 2030343, "TopicalTrustFlow" : 51, "LinksFromRefDomains" : 58829547, "RefDomains" : 17665, "Pages" : 217622 },{ "Topic" : "Business/Business Services", "Links" : 1290956, "TopicalTrustFlow" : 51, "LinksFromRefDomains" : 41566171, "RefDomains" : 12760, "Pages" : 60927 },{ "Topic" : "Arts/Education", "Links" : 742563, "TopicalTrustFlow" : 51, "LinksFromRefDomains" : 24907442, "RefDomains" : 7382, "Pages" : 34246 },{ "Topic" : "Computers/Security", "Links" : 695176, "TopicalTrustFlow" : 51, "LinksFromRefDomains" : 27336373, "RefDomains" : 13499, "Pages" : 32462 },{ "Topic" : "Business/Food and Related Products", "Links" : 431704, "TopicalTrustFlow" : 51, "LinksFromRefDomains" : 14495694, "RefDomains" : 7701, "Pages" : 26083 },{ "Topic" : "Science/Physics", "Links" : 401473, "TopicalTrustFlow" : 51, "LinksFromRefDomains" : 6706512, "RefDomains" : 4058, "Pages" : 26920 },{ "Topic" : "Recreation/Aviation", "Links" : 327016, "TopicalTrustFlow" : 51, "LinksFromRefDomains" : 16278243, "RefDomains" : 3757, "Pages" : 9842 },{ "Topic" : "Society/Folklore", "Links" : 79843, "TopicalTrustFlow" : 51, "LinksFromRefDomains" : 8296438, "RefDomains" : 1367, "Pages" : 6970 },{ "Topic" : "Home/Family", "Links" : 742073, "TopicalTrustFlow" : 50, "LinksFromRefDomains" : 23891936, "RefDomains" : 12071, "Pages" : 54136 },{ "Topic" : "Arts/Visual Arts", "Links" : 607967, "TopicalTrustFlow" : 50, "LinksFromRefDomains" : 19006038, "RefDomains" : 11521, "Pages" : 45113 },{ "Topic" : "Shopping/Clothing", "Links" : 323431, "TopicalTrustFlow" : 50, "LinksFromRefDomains" : 24545445, "RefDomains" : 4419, "Pages" : 20545 },{ "Topic" : "Health/Animal", "Links" : 148792, "TopicalTrustFlow" : 50, "LinksFromRefDomains" : 4840480, "RefDomains" : 2803, "Pages" : 16609 },{ "Topic" : "Computers/Software/Globalization", "Links" : 82178, "TopicalTrustFlow" : 50, "LinksFromRefDomains" : 4019290, "RefDomains" : 1035, "Pages" : 13932 }]}}}